setup.cfg
setup.py
avrobase/__init__.py
avrobase/record.py
avrobase/version.py
avrobase.egg-info/PKG-INFO
avrobase.egg-info/SOURCES.txt
avrobase.egg-info/dependency_links.txt
avrobase.egg-info/top_level.txt