Metadata-Version: 1.1
Name: avrobase
Version: 0.0.1
Summary: Python Classes for Avro
Home-page: https://github.com/scottbelden/avrobase
Author: Scott Belden
Author-email: scottabelden@gmail.com
License: Apache 2.0
Download-URL: https://github.com/scottbelden/avrobase/tarball/0.0.1
Platform: UNKNOWN
